pactools/__init__.py
pactools/bandpass_filter.py
pactools/comodulogram.py
pactools/delay_estimator.py
pactools/grid_search.py
pactools/mne_api.py
pactools/peak_locking.py
pactools/references.py
pactools/simulate_pac.py
pactools/dar_model/__init__.py
pactools/dar_model/base_dar.py
pactools/dar_model/base_lattice.py
pactools/dar_model/dar.py
pactools/dar_model/har.py
pactools/dar_model/preprocess.py
pactools/dar_model/stable_dar.py
pactools/utils/__init__.py
pactools/utils/arma.py
pactools/utils/carrier.py
pactools/utils/dehummer.py
pactools/utils/deprecation.py
pactools/utils/fir.py
pactools/utils/maths.py
pactools/utils/parallel.py
pactools/utils/peak_finder.py
pactools/utils/pink_noise.py
pactools/utils/progress_bar.py
pactools/utils/spectrum.py
pactools/utils/testing.py
pactools/utils/validation.py
pactools/utils/viz.py
pactools-0.3.1.dist-info/LICENSE
pactools-0.3.1.dist-info/METADATA
pactools-0.3.1.dist-info/WHEEL
pactools-0.3.1.dist-info/top_level.txt
pactools-0.3.1.dist-info/RECORD
