Metadata-Version: 1.2
Name: pactools
Version: 0.3.1
Summary: Estimation of phase-amplitude coupling (PAC) in neural time series,
Home-page: http://github.com/pactools/pactools
Maintainer: Tom Dupre la Tour
Maintainer-email: tom.dupre-la-tour@m4x.org
License: BSD (3-clause)
Download-URL: https://github.com/pactools/pactools.git
Platform: UNKNOWN
